dropmail/__init__.py
dropmail/__version__.py
dropmail/client.py
dropmail/exceptions.py
dropmail-1.0.3.dist-info/METADATA
dropmail-1.0.3.dist-info/WHEEL
dropmail-1.0.3.dist-info/top_level.txt
dropmail-1.0.3.dist-info/RECORD
